streamlit_nej_datepicker/__init__.py
streamlit_nej_datepicker/nej_datepicker.py
streamlit_nej_datepicker/utils.py
streamlit_nej_datepicker/frontend/dist/index.html
streamlit_nej_datepicker/frontend/dist/assets/index-BI6OzgoY.js
streamlit_nej_datepicker/frontend/dist/assets/index-XxNEv93q.css
streamlit_nej_datepicker-1.0.3.dist-info/LICENSE
streamlit_nej_datepicker-1.0.3.dist-info/METADATA
streamlit_nej_datepicker-1.0.3.dist-info/WHEEL
streamlit_nej_datepicker-1.0.3.dist-info/top_level.txt
streamlit_nej_datepicker-1.0.3.dist-info/RECORD
