Metadata-Version: 2.1
Name: streamlit-nej-datepicker
Version: 1.0.3
Summary: A simple and configurable datepicker for Streamlit with support of both Gregorian and Jalali calendar.
Home-page: https://github.com/nejadipour/streamlit-nej-datepicker
Author: Alireza Nejadipour
Author-email: nejadipour@gmail.com
Project-URL: Bug Tracker, https://github.com/nejadipour/streamlit-nej-datepicker/issues
Requires-Python: >=3.6
License-File: LICENSE
Requires-Dist: streamlit (>=0.63)
Requires-Dist: jdatetime
Requires-Dist: pydantic (>=2.0)
